{"code": 0, "message": "0", "ttl": 1, "data": {"list": [{"music_id": "MA497947980779780937", "music_title": "\u4e0d\u7720\u4e4b\u591c", "singer": "HOYO-MiX,\u5f20\u6770", "album": "\u5d29\u574f\u661f\u7a79\u94c1\u9053-\u4e0d\u7720\u4e4b\u591c WHITE NIGHT", "mv_aid": 0, "mv_bvid": "", "mv_cover": "https://i0.hdslb.com/bfs/station_src/music_metadata/08cb25bbafd88172d827bea68a5f48db.jpg", "heat": 11055555, "rank": 1, "can_listen": false, "recommendation": "", "creation_aid": 924325633, "creation_bvid": "BV12T4y147sd", "creation_cover": "http://i1.hdslb.com/bfs/archive/1de7fa7ad32b05c9cd1a78cf3e563a571aefa67b.jpg", "creation_title": "\u4e0d\u7720\u4e4b\u591c \u7ffb\u5531", "creation_up": 11073, "creation_nickname": "hanser", "creation_duration": 94, "creation_play": 4357832, "vt": 0, "creation_reason": "\u6b4c\u66f2\u6f14\u5531", "achievements": ["\u65b0\u664b\u4e0a\u699c", "\u6700\u9ad8\u6392\u540d1"], "material_id": 0, "material_use_num": 0, "material_duration": 0, "material_show": 1, "song_type": 2, "is_vt": 0, "vt_display": "", "last_rank": 0}, {"music_id": "MA436907948753578382", "music_title": "\u30db\u30c9\u30e2\u30a8\u30b7\u30c6\u30a3 (\u5e06\u5df4\u5e02)", "singer": "\u666f\u5c71\u5c06\u592a", "album": "\u30cb\u30f3\u30c6\u30f3\u30c9\u30fcDS \u30dd\u30b1\u30e2\u30f3\u30d6\u30e9\u30c3\u30af\u30fb\u30db\u30ef\u30a4\u30c8 \u30b9\u30fc\u30d1\u30fc\u30df\u30e5\u30fc\u30b8\u30c3\u30af\u30b3\u30ec\u30af\u30b7\u30e7\u30f3 (\u53e3\u888b\u5996\u602a\u9ed1\u767d\u97f3\u4e50\u539f\u58f0)", "mv_aid": 0, "mv_bvid": "", "mv_cover": "https://i0.hdslb.com/bfs/station_src/music_metadata/f093c67f00d81fdcfb39c431e6e21581.jpg", "heat": 1800867, "rank": 2, "can_listen": false, "recommendation": "", "creation_aid": 1250226142, "creation_bvid": "BV1jJ4m147du", "creation_cover": "http://i2.hdslb.com/bfs/archive/9698904cea48fe8119173232024245b8683b8b19.jpg", "creation_title": "\u65e0\u7259\u4ed4\uff0c\u4f46\u662f\u5728\u7eb8\u4e0a", "creation_up": 360861964, "creation_nickname": "\u68d5\u4e0e\u70709", "creation_duration": 70, "creation_play": 383222, "vt": 0, "creation_reason": "\u52a8\u753b\u521b\u4f5c", "achievements": ["\u672c\u671f\u6392\u540d\u21916", "\u6700\u9ad8\u6392\u540d2"], "material_id": 0, "material_use_num": 0, "material_duration": 0, "material_show": 1, "song_type": 2, "is_vt": 0, "vt_display": "", "last_rank": 8}, {"music_id": "MA423615974915196759", "music_title": "All My People", "singer": "Alexandra Stan,Manilla Maniacs", "album": "All My People", "mv_aid": 0, "mv_bvid": "", "mv_cover": "https://i0.hdslb.com/bfs/station_src/music_metadata/d7ef12ca41d0500f51ed82bbfc54eb23.jpg", "heat": 1640617, "rank": 3, "can_listen": false, "recommendation": "", "creation_aid": 452506376, "creation_bvid": "BV1gj411H7ff", "creation_cover": "http://i2.hdslb.com/bfs/archive/7c171c1b21379b61b9ac54e79ad1c687763f5045.jpg", "creation_title": "\u81f4 \u547d \u5c55 \u5f00\uff0c\u5750 \u6740 \u535a \u5f92 \uff01", "creation_up": 1172935837, "creation_nickname": "\u641e\u4e0d\u61c2\u7684\u9e7f", "creation_duration": 61, "creation_play": 2488556, "vt": 0, "creation_reason": "\u52a8\u753b\u521b\u4f5c", "achievements": ["\u672c\u671f\u6392\u540d\u21931", "\u6700\u9ad8\u6392\u540d1"], "material_id": 0, "material_use_num": 0, "material_duration": 0, "material_show": 1, "song_type": 2, "is_vt": 0, "vt_display": "", "last_rank": 2}, {"music_id": "MA477956718395950652", "music_title": "\u79bb\u522b\u5f00\u51fa\u82b1", "singer": "\u5c31\u662f\u5357\u65b9\u51ef", "album": "\u79bb\u522b\u5f00\u51fa\u82b1", "mv_aid": 0, "mv_bvid": "", "mv_cover": "https://i0.hdslb.com/bfs/station_src/music_metadata/3a915678bd3c1e1d82db1cf5c14239ed.jpg", "heat": 1427934, "rank": 4, "can_listen": false, "recommendation": "", "creation_aid": 494877986, "creation_bvid": "BV11N411V7KH", "creation_cover": "http://i2.hdslb.com/bfs/archive/5e9edbf30b7c675b0c9b7a8dabeffef584617959.jpg", "creation_title": "\u3010ai\u7ffb\u5531\u3011\u80e1\u6843\u300a\u5f53\u79bb\u522b\u5f00\u51fa\u82b1\u300b\u5f53\u79bb\u522b\u5f00\u51fa\u82b1 \u4f38\u51fa\u65b0\u957f\u7684\u679d\u6860 \u50cf\u51ac\u53bb\u53c8\u79cb\u6765 \u7b49\u5f85\u5fc3\u96ea\u878d\u5316", "creation_up": 1821669896, "creation_nickname": "\u662f\u753b\u7396\u5440", "creation_duration": 242, "creation_play": 7999045, "vt": 0, "creation_reason": "\u6b4c\u66f2\u6f14\u5531", "achievements": ["\u672c\u671f\u6392\u540d\u21912", "\u6700\u9ad8\u6392\u540d1"], "material_id": 0, "material_use_num": 0, "material_duration": 0, "material_show": 1, "song_type": 2, "is_vt": 0, "vt_display": "", "last_rank": 6}, {"music_id": "MA406539453952182640", "music_title": "\u5b89\u548c\u6865", "singer": "\u5b8b\u51ac\u91ce", "album": "\u5b89\u548c\u6865\u5317", "mv_aid": 0, "mv_bvid": "", "mv_cover": "https://i0.hdslb.com/bfs/station_src/music_metadata/38e219c46e6bc356521a3889c4c8a946.jpg", "heat": 1269764, "rank": 5, "can_listen": false, "recommendation": "", "creation_aid": 895728268, "creation_bvid": "BV1PA4y1R7fN", "creation_cover": "http://i2.hdslb.com/bfs/archive/ca26027ac4665c88b9af0c5a3bf87e90041b28a3.jpg", "creation_title": "\u3010\u6307\u5f39\u5409\u4ed6\u3011\u5b89\u548c\u6865\u5b8c\u6574\u7248\uff0c\u6211\u77e5\u9053\u518d\u4e5f\u56de\u4e0d\u53bb", "creation_up": 87300577, "creation_nickname": "z\u6770\u54e5", "creation_duration": 254, "creation_play": 1267188, "vt": 0, "creation_reason": "\u5668\u4e50\u6f14\u594f", "achievements": ["\u672c\u671f\u6392\u540d\u21931", "\u6700\u9ad8\u6392\u540d4"], "material_id": 0, "material_use_num": 0, "material_duration": 0, "material_show": 1, "song_type": 2, "is_vt": 0, "vt_display": "", "last_rank": 4}, {"music_id": "MA497377429254339161", "music_title": "Wife", "singer": "(G)I-DLE ", "album": "Wife", "mv_aid": 879124834, "mv_bvid": "BV1TN4y1H7v7", "mv_cover": "https://i0.hdslb.com/bfs/station_src/music_metadata/81d8610154343cb25b244605c7b2e4c9.jpg", "heat": 1053806, "rank": 6, "can_listen": true, "recommendation": "", "creation_aid": 879124834, "creation_bvid": "BV1TN4y1H7v7", "creation_cover": "http://i0.hdslb.com/bfs/archive/e1ecb8cf8acfd2baa4a187f99f4dbb444ef0cf49.jpg", "creation_title": "\u3010(G)I-DLE\u3011[M/V] - 'Wife'", "creation_up": 624243924, "creation_nickname": "i-dle_official", "creation_duration": 138, "creation_play": 10483063, "vt": 0, "creation_reason": "\u5b98\u65b9MV", "achievements": ["\u65b0\u664b\u4e0a\u699c", "\u6700\u9ad8\u6392\u540d6"], "material_id": 0, "material_use_num": 0, "material_duration": 0, "material_show": 1, "song_type": 2, "is_vt": 0, "vt_display": "", "last_rank": 0}, {"music_id": "MA495628723454757953", "music_title": "\u518d\u6b21\u4e0e\u4f60\u540c\u884c", "singer": "\u718a\u5927/\u718a\u4e8c/\u5149\u5934\u5f3a", "album": "\u518d\u6b21\u4e0e\u4f60\u540c\u884c", "mv_aid": 923970394, "mv_bvid": "BV1ET4y1h7QB", "mv_cover": "https://i0.hdslb.com/bfs/station_src/music_metadata/cd5fdba2180d7b5e2715947e7f03f7b1.jpg", "heat": 772463, "rank": 7, "can_listen": true, "recommendation": "", "creation_aid": 538910585, "creation_bvid": "BV13i4y1q76j", "creation_cover": "http://i2.hdslb.com/bfs/archive/d5062edfbbb273d377a34d9f2051b6149ace8dde.jpg", "creation_title": "\u4f60\u4ece\u672a\u79bb\u53bb\uff0c\u7ec8\u4f1a\u518d\u6b21\u4e0e\u4f60\u540c\u884c\uff01", "creation_up": 334939754, "creation_nickname": "\u963f\u5361\u5927\u6587", "creation_duration": 65, "creation_play": 501469, "vt": 0, "creation_reason": "\u6b4c\u66f2\u6f14\u5531", "achievements": ["\u672c\u671f\u6392\u540d\u21936", "\u6700\u9ad8\u6392\u540d1"], "material_id": 0, "material_use_num": 0, "material_duration": 0, "material_show": 1, "song_type": 2, "is_vt": 0, "vt_display": "", "last_rank": 1}, {"music_id": "MA465937631415381403", "music_title": "Void", "singer": "Hongzhe_Cui", "album": "Void", "mv_aid": 789312452, "mv_bvid": "BV15C4y1Z7bL", "mv_cover": "https://i0.hdslb.com/bfs/station_src/music_metadata/6e2ecf1ad8562d9093fd7102de254cff.jpg", "heat": 744574, "rank": 8, "can_listen": true, "recommendation": "", "creation_aid": 790240184, "creation_bvid": "BV1My4y1A7UH", "creation_cover": "http://i2.hdslb.com/bfs/archive/ebc5fc68069dbf8bf9b4fa7f6218784431d9bb36.jpg", "creation_title": "\u300a\u5982\u5c65\u8584\u51b0\u306e\u5c0f\u66f2\u300b\u300a\u6df7\u526a\u306e\u5c0f\u66f2\u300bVoid \u2014\u2014 Hongzhe_Cui", "creation_up": 450224914, "creation_nickname": "\u611f\u540c\u306e\u8eab\u517d", "creation_duration": 209, "creation_play": 1384590, "vt": 0, "creation_reason": "\u97f3\u4e50MV", "achievements": ["\u672c\u671f\u6392\u540d\u219111", "\u6700\u9ad8\u6392\u540d4"], "material_id": 0, "material_use_num": 0, "material_duration": 0, "material_show": 1, "song_type": 2, "is_vt": 0, "vt_display": "", "last_rank": 19}, {"music_id": "MA487501277299794131", "music_title": "We Never", "singer": "Hi Noise", "album": "We Never EP", "mv_aid": 0, "mv_bvid": "", "mv_cover": "https://i0.hdslb.com/bfs/station_src/music_metadata/a1a5df6a8b685b6ad1ccfd1bec404342.jpg", "heat": 724188, "rank": 9, "can_listen": false, "recommendation": "", "creation_aid": 707772759, "creation_bvid": "BV1cQ4y1g72z", "creation_cover": "http://i2.hdslb.com/bfs/archive/74171ff30716563db9d19fc7ba01ec1ddf1c58f5.jpg", "creation_title": "\u8fd9\u5c31\u662f\u5fc3\u5982\u6b62\u6c34\u5417\uff1f", "creation_up": 3493143397796114, "creation_nickname": "\u6211\u53eb\u72d9\u4ed9\u90fd\u5416", "creation_duration": 118, "creation_play": 209104, "vt": 0, "creation_reason": "\u5f71\u89c6\u526a\u8f91", "achievements": ["\u672c\u671f\u6392\u540d\u21932", "\u6700\u9ad8\u6392\u540d7"], "material_id": 0, "material_use_num": 0, "material_duration": 0, "material_show": 1, "song_type": 2, "is_vt": 0, "vt_display": "", "last_rank": 7}, {"music_id": "MA473303681572306006", "music_title": "TIRED OF PROBLEMS (Explicit)", "singer": "Glichery,NUEKI,TOLCHONOV", "album": "TIRED OF PROBLEMS (Explicit)", "mv_aid": 0, "mv_bvid": "", "mv_cover": "http://i0.hdslb.com/bfs/station_src/music_metadata/3cc0bd5ae5d6c1b3eb625c1c77b64365.jpg", "heat": 705342, "rank": 10, "can_listen": false, "recommendation": "", "creation_aid": 0, "creation_bvid": "", "creation_cover": "", "creation_title": "", "creation_up": 0, "creation_nickname": "", "creation_duration": 0, "creation_play": 0, "vt": 0, "creation_reason": "", "achievements": ["\u91cd\u56de\u699c\u5355", "\u6700\u9ad8\u6392\u540d3"], "material_id": 0, "material_use_num": 0, "material_duration": 0, "material_show": 1, "song_type": 2, "is_vt": 0, "vt_display": "", "last_rank": 3}, {"music_id": "MA400017093531020491", "music_title": "\u5170\u4ead\u5e8f", "singer": "\u5468\u6770\u4f26", "album": "\u9b54\u6770\u5ea7", "mv_aid": 0, "mv_bvid": "", "mv_cover": "https://i0.hdslb.com/bfs/station_src/music_metadata/a03f7d174c3b01e4c6b3907a115c5434.jpg", "heat": 631931, "rank": 11, "can_listen": false, "recommendation": "", "creation_aid": 564412506, "creation_bvid": "BV1zv4y1q7RT", "creation_cover": "http://i1.hdslb.com/bfs/archive/d8997dfdc8794cfc490b563b80c65399410e075b.jpg", "creation_title": "\u7237\u7237\u7684\u4e8c\u80e1\u72ec\u594f\u300a\u5170\u4ead\u5e8f\u300bcover\u5468\u6770\u4f26", "creation_up": 588204480, "creation_nickname": "\u8001\u738b\u54c6\u6765\u54aa", "creation_duration": 139, "creation_play": 1419767, "vt": 0, "creation_reason": "\u97f3\u4e50MV", "achievements": ["\u91cd\u56de\u699c\u5355", "\u6700\u9ad8\u6392\u540d4"], "material_id": 0, "material_use_num": 0, "material_duration": 0, "material_show": 1, "song_type": 2, "is_vt": 0, "vt_display": "", "last_rank": 13}, {"music_id": "MA489150070382426454", "music_title": "\u6211\u671f\u5f85\u7684\u4e0d\u662f\u96ea (\u800c\u662f\u6709\u4f60\u7684\u51ac\u5929)", "singer": "\u5f20\u5999\u683c", "album": "\u6211\u671f\u5f85\u7684\u4e0d\u662f\u96ea (\u800c\u662f\u6709\u4f60\u7684\u51ac\u5929)", "mv_aid": 0, "mv_bvid": "", "mv_cover": "https://i0.hdslb.com/bfs/station_src/music_metadata/57788738f0d245f29f094f2979d4dfd8.jpg", "heat": 625630, "rank": 12, "can_listen": false, "recommendation": "", "creation_aid": 368032332, "creation_bvid": "BV1B94y1c7XV", "creation_cover": "http://i1.hdslb.com/bfs/archive/d72b794be82e21167d2fbcfb1b0c9e894404e102.jpg", "creation_title": "[\u8bf8\u845b\u4eae]\u201c\u6211\u671f\u5f85\u7684\u4e0d\u662f\u96ea\uff0c\u8fd8\u662f\u90a3\u9057\u61be\u7684\u5317\u4f10\u3002\u2033(\u5386\u53f2\u55b5\u7248)", "creation_up": 1323765256, "creation_nickname": "\u5386\u53f2\u8881", "creation_duration": 164, "creation_play": 1414438, "vt": 0, "creation_reason": "\u97f3\u4e50\u521b\u4f5c", "achievements": ["\u91cd\u56de\u699c\u5355", "\u6700\u9ad8\u6392\u540d1"], "material_id": 0, "material_use_num": 0, "material_duration": 0, "material_show": 1, "song_type": 2, "is_vt": 0, "vt_display": "", "last_rank": 15}, {"music_id": "MA497561434746551113", "music_title": "Love wins all", "singer": "IU", "album": "Love wins all", "mv_aid": 0, "mv_bvid": "", "mv_cover": "https://i0.hdslb.com/bfs/station_src/music_metadata/3e7b5201a1d11493d8b2b9fe0595b67c.jpg", "heat": 580467, "rank": 13, "can_listen": false, "recommendation": "", "creation_aid": 794206933, "creation_bvid": "BV13C4y1k7ph", "creation_cover": "http://i2.hdslb.com/bfs/archive/79f070d7a4ec2164ec20788808528a4157ec3c0d.jpg", "creation_title": "IU\u56de\u5f52\u5148\u884c\u66f2Love wins all MV\u516c\u5f00", "creation_up": 16720403, "creation_nickname": "pcyxjy", "creation_duration": 324, "creation_play": 2862917, "vt": 0, "creation_reason": "\u97f3\u4e50MV", "achievements": ["\u65b0\u664b\u4e0a\u699c", "\u6700\u9ad8\u6392\u540d13"], "material_id": 0, "material_use_num": 0, "material_duration": 0, "material_show": 1, "song_type": 2, "is_vt": 0, "vt_display": "", "last_rank": 0}, {"music_id": "MA400015807137983691", "music_title": "Take Me Hand", "singer": "DAISHI DANCE,C\u00e9cile Corbel", "album": "WONDER Tourism", "mv_aid": 0, "mv_bvid": "", "mv_cover": "http://i0.hdslb.com/bfs/station_src/music_metadata/68b2e19db3b3b0456cb561e9e80e9165.jpg", "heat": 551175, "rank": 14, "can_listen": false, "recommendation": "", "creation_aid": 89344037, "creation_bvid": "BV177411n7LP", "creation_cover": "http://i0.hdslb.com/bfs/archive/498cd42d3eb10f6ef4d3be4a698000e8f8476435.jpg", "creation_title": "\u5f53\u6211\u7b11\u7684\u90a3\u4e00\u523b\uff0c\u8bf7\u81ea\u5907\u7eb8\u5dfe\uff01", "creation_up": 454911170, "creation_nickname": "\u6478\u9c7c\u7684\u767d\u9f20\u540c\u5b66", "creation_duration": 259, "creation_play": 14917227, "vt": 0, "creation_reason": "\u81ea\u5236MV", "achievements": ["\u672c\u671f\u6392\u540d\u21935", "\u6700\u9ad8\u6392\u540d9"], "material_id": 0, "material_use_num": 0, "material_duration": 0, "material_show": 1, "song_type": 2, "is_vt": 0, "vt_display": "", "last_rank": 9}, {"music_id": "MA497368160647793251", "music_title": "\u6700\u540e\u4e4b\u540e", "singer": "\u5b59\u71d5\u59ff,\u738b\u8005\u8363\u8000", "album": "\u6700\u540e\u4e4b\u540e", "mv_aid": 326736346, "mv_bvid": "BV1vw411j7wB", "mv_cover": "https://i0.hdslb.com/bfs/station_src/music_metadata/05794184e467033b3843a7c269b0acaa.jpg", "heat": 549898, "rank": 15, "can_listen": true, "recommendation": "", "creation_aid": 326736346, "creation_bvid": "BV1vw411j7wB", "creation_cover": "http://i1.hdslb.com/bfs/archive/c91353ccd2e4127a705e50298c7a8caadd7b3084.jpg", "creation_title": "\u5b59\u71d5\u59ff | \u738b\u8005\u8363\u8000\u7425\u73c0\u7eaa\u5143\u4e3b\u9898\u66f2\u300a\u6700\u540e\u4e4b\u540e\u300b", "creation_up": 32708543, "creation_nickname": "\u5927\u5bb6\u7684\u97f3\u4e50\u673a", "creation_duration": 282, "creation_play": 1474309, "vt": 0, "creation_reason": "\u5b98\u65b9MV", "achievements": ["\u65b0\u664b\u4e0a\u699c", "\u6700\u9ad8\u6392\u540d15"], "material_id": 0, "material_use_num": 0, "material_duration": 0, "material_show": 1, "song_type": 2, "is_vt": 0, "vt_display": "", "last_rank": 0}, {"music_id": "MA409541174550866884", "music_title": "\u9e33\u9e2f\u620f", "singer": "Babystop_\u5c71\u7af9,\u4f0a\u7b11", "album": "\u9e33\u9e2f\u620f", "mv_aid": 0, "mv_bvid": "", "mv_cover": "https://i0.hdslb.com/bfs/station_src/music_metadata/647e29709e3f25b2f583b9e59e39635c.jpg", "heat": 529757, "rank": 16, "can_listen": false, "recommendation": "", "creation_aid": 827767778, "creation_bvid": "BV1tg4y1N7XW", "creation_cover": "http://i2.hdslb.com/bfs/archive/14da14bd530985e55332ff9e47f963255aceeb37.jpg", "creation_title": "\u300a\u9e33\u9e2f\u620f\u300b\u6d45\u6d45\u73a9\u800d\uff5e\uff5e\uff5e", "creation_up": 345630501, "creation_nickname": "\u9ec4\u9f84", "creation_duration": 221, "creation_play": 717884, "vt": 0, "creation_reason": "\u6b4c\u66f2\u6f14\u5531", "achievements": ["\u91cd\u56de\u699c\u5355", "\u6700\u9ad8\u6392\u540d11"], "material_id": 0, "material_use_num": 0, "material_duration": 0, "material_show": 1, "song_type": 2, "is_vt": 0, "vt_display": "", "last_rank": 18}, {"music_id": "MA406619688638913202", "music_title": "HEAVEN", "singer": "Ailee", "album": "Heaven", "mv_aid": 0, "mv_bvid": "", "mv_cover": "https://i0.hdslb.com/bfs/station_src/music_metadata/1d0bccda7d337b4d3e52951a89d774bb.jpg", "heat": 525615, "rank": 17, "can_listen": false, "recommendation": "", "creation_aid": 876530978, "creation_bvid": "BV1sN4y12763", "creation_cover": "http://i1.hdslb.com/bfs/archive/fcde298679fa11af9afe534d285b6a7bc4986e40.jpg", "creation_title": "\u201c\u521d\u8bc6\u4e0d\u77e5\u66f2\u4e2d\u610f\uff0c\u518d\u542c\u5df2\u662f\u66f2\u4e2d\u4eba\u201d\u2014\u300aHeaven\u300b", "creation_up": 322041385, "creation_nickname": "\u55f7\u55f7\u53eb\u7684\u73c8\u5c0f\u9e7f", "creation_duration": 100, "creation_play": 1753651, "vt": 0, "creation_reason": "\u52a8\u753b\u521b\u4f5c", "achievements": ["\u91cd\u56de\u699c\u5355", "\u6700\u9ad8\u6392\u540d10"], "material_id": 0, "material_use_num": 0, "material_duration": 0, "material_show": 1, "song_type": 2, "is_vt": 0, "vt_display": "", "last_rank": 10}, {"music_id": "MA409255375045454174", "music_title": "\u60ac\u6eba", "singer": "\u845b\u4e1c\u742a", "album": "\u7b2c\u4e8c\u8857\u533a", "mv_aid": 712792622, "mv_bvid": "BV1yD4y1Q73y", "mv_cover": "https://i0.hdslb.com/bfs/station_src/music_metadata/921f8acd665ac15980fb1e90b8b82e2f.jpg", "heat": 519806, "rank": 18, "can_listen": true, "recommendation": "", "creation_aid": 241353533, "creation_bvid": "BV1Xe411H7Jn", "creation_cover": "http://i1.hdslb.com/bfs/archive/5eb2ca46738825aae352a9ef2071d1b0565a5485.png", "creation_title": "\u201d\u674e\u767d\uff0c\u4e00\u4e2a\u60ca\u4e16\u7684\u2026\u2026\u72c2\u5f92\u201d", "creation_up": 34357028, "creation_nickname": "\u80860\u5341", "creation_duration": 196, "creation_play": 1927449, "vt": 0, "creation_reason": "\u52a8\u753b\u521b\u4f5c", "achievements": ["\u672c\u671f\u6392\u540d\u21936", "\u6700\u9ad8\u6392\u540d1"], "material_id": 0, "material_use_num": 0, "material_duration": 0, "material_show": 1, "song_type": 2, "is_vt": 0, "vt_display": "", "last_rank": 12}, {"music_id": "MA413046147473510983", "music_title": "Call of Silence", "singer": "\u6fa4\u91ce\u5f18\u4e4b", "album": "TV\u30a2\u30cb\u30e1\u300c\u9032\u6483\u306e\u5de8\u4eba\u300dSeason 2 \u30aa\u30ea\u30b8\u30ca\u30eb\u30b5\u30a6\u30f3\u30c9\u30c8\u30e9\u30c3\u30af \u97f3\u697d:\u6fa4\u91ce\u5f18\u4e4b", "mv_aid": 0, "mv_bvid": "", "mv_cover": "https://i0.hdslb.com/bfs/station_src/music_metadata/3a38dcfa1d487faefba7dd15ac0b1f80.jpg", "heat": 516051, "rank": 19, "can_listen": false, "recommendation": "", "creation_aid": 273365353, "creation_bvid": "BV1hF41197gp", "creation_cover": "http://i2.hdslb.com/bfs/archive/d5cf1ec2b729b80dd9d68e75a3a27f39cef56b74.jpg", "creation_title": "\u3010\ud835\ude3e\ud835\ude56\ud835\ude61\ud835\ude61 \ud835\ude4a\ud835\ude5b \ud835\ude4e\ud835\ude5e\ud835\ude61\ud835\ude5a\ud835\ude63\ud835\ude58\ud835\ude5a /\u5d29\u574f3\u3011\u7eb5\u4f7f\u9ed1\u4e91\u853d\u65e5\uff0c\u6211\u4e5f\u8981\u71c3\u70e7\u5929\u7a7a\uff0c\u5e26\u4f60\u627e\u5230\u56de\u5bb6\u7684\u8def", "creation_up": 384160166, "creation_nickname": "\u5c0f\u9e1f\u6e38\u9999\u309c", "creation_duration": 159, "creation_play": 414212, "vt": 0, "creation_reason": "BGM\u6df7\u526a", "achievements": ["\u91cd\u56de\u699c\u5355", "\u6700\u9ad8\u6392\u540d4"], "material_id": 0, "material_use_num": 0, "material_duration": 0, "material_show": 1, "song_type": 2, "is_vt": 0, "vt_display": "", "last_rank": 20}, {"music_id": "MA498077304979749793", "music_title": "\u6211\u662f\u4f60\u7684\u5c0f\u72d7", "singer": "\u897f\u5f6c", "album": "\u300a\u6211\u662f\u4f60\u7684\u5c0f\u72d7\u300b\u6f2b\u753b\u540c\u540d\u4e3b\u9898\u66f2", "mv_aid": 836386338, "mv_bvid": "BV1og4y1m7aT", "mv_cover": "https://i0.hdslb.com/bfs/station_src/music_metadata/d3214f59c072c73e8fe48314fbe75c01.jpg", "heat": 504641, "rank": 20, "can_listen": true, "recommendation": "", "creation_aid": 836386338, "creation_bvid": "BV1og4y1m7aT", "creation_cover": "http://i1.hdslb.com/bfs/archive/f6f2d869c16bc584b9f5574207f51656d2f542e5.jpg", "creation_title": "\u4e16\u754c\u7834\u7834\u70c2\u70c2\uff0c\u5c0f\u72d7\u7f1d\u7f1d\u8865\u8865\u3002\u4e00\u9996\u5173\u4e8e\u5c0f\u72d7\u7684\u6b4c~", "creation_up": 358868925, "creation_nickname": "\u897f\u5f6c\u897f\u5f6c", "creation_duration": 130, "creation_play": 1157132, "vt": 0, "creation_reason": "\u5b98\u65b9MV", "achievements": ["\u65b0\u664b\u4e0a\u699c", "\u6700\u9ad8\u6392\u540d20"], "material_id": 0, "material_use_num": 0, "material_duration": 0, "material_show": 1, "song_type": 2, "is_vt": 0, "vt_display": "", "last_rank": 0}], "list_id": 153, "version": 4}}